{
  "configVersion": 1,
  "timestamp": 1630812874275,
  "index": "/index.html",
  "assetGroups": [
    {
      "name": "app",
      "installMode": "prefetch",
      "updateMode": "prefetch",
      "cacheQueryOptions": {
        "ignoreVary": true
      },
      "urls": [
        "/common-es2015.a3af4c990831a830edd0.js",
        "/common-es5.a3af4c990831a830edd0.js",
        "/default~AlchemiaStruggle~index-es2015.0224f6625aedc30e083f.js",
        "/default~AlchemiaStruggle~index-es5.0224f6625aedc30e083f.js",
        "/default~AngelGear~index-es2015.4459dfea6bfa2b9ff8b2.js",
        "/default~AngelGear~index-es5.4459dfea6bfa2b9ff8b2.js",
        "/default~AnimaAnimus~index-es2015.9bca9ed50b1b0f200891.js",
        "/default~AnimaAnimus~index-es5.9bca9ed50b1b0f200891.js",
        "/default~BattleTech~index-es2015.6fa618469cd2ddaf67cb.js",
        "/default~BattleTech~index-es5.6fa618469cd2ddaf67cb.js",
        "/default~BeginningIdol_Korean~index-es2015.322c54b2b7565e07da4e.js",
        "/default~BeginningIdol_Korean~index-es5.322c54b2b7565e07da4e.js",
        "/default~BeginningIdol~index-es2015.07bb12b4845fe6f5a77f.js",
        "/default~BeginningIdol~index-es5.07bb12b4845fe6f5a77f.js",
        "/default~BlindMythos~index-es2015.6587af6166e7e8380683.js",
        "/default~BlindMythos~index-es5.6587af6166e7e8380683.js",
        "/default~BloodCrusade~index-es2015.aee75fb0df01bc4c6149.js",
        "/default~BloodCrusade~index-es5.aee75fb0df01bc4c6149.js",
        "/default~BloodMoon~index-es2015.2423cc88233b62554acb.js",
        "/default~BloodMoon~index-es5.2423cc88233b62554acb.js",
        "/default~ColossalHunter~index-es2015.732e36f2db14d4e675e2.js",
        "/default~ColossalHunter~index-es5.732e36f2db14d4e675e2.js",
        "/default~Cthulhu7th~index-es2015.15f1bfc4e4859f67881d.js",
        "/default~Cthulhu7th~index-es5.15f1bfc4e4859f67881d.js",
        "/default~DeadlineHeroes~index-es2015.02c25655b2808f8d12f1.js",
        "/default~DeadlineHeroes~index-es5.02c25655b2808f8d12f1.js",
        "/default~DemonParasite~index-es2015.e6ae355451aaf002e076.js",
        "/default~DemonParasite~index-es5.e6ae355451aaf002e076.js",
        "/default~DesperateRun~index-es2015.1678bf80fb05d5414fb5.js",
        "/default~DesperateRun~index-es5.1678bf80fb05d5414fb5.js",
        "/default~DoubleCross_Korean~index-es2015.8f61f652e1412d02ed5d.js",
        "/default~DoubleCross_Korean~index-es5.8f61f652e1412d02ed5d.js",
        "/default~DoubleCross~index-es2015.83a393c976d3c5f78138.js",
        "/default~DoubleCross~index-es5.83a393c976d3c5f78138.js",
        "/default~Elysion~index-es2015.38bc3763bd949da1ab5e.js",
        "/default~Elysion~index-es5.38bc3763bd949da1ab5e.js",
        "/default~FilledWith~index-es2015.fa9e9699e9e0d95f2ba9.js",
        "/default~FilledWith~index-es5.fa9e9699e9e0d95f2ba9.js",
        "/default~Garako~index-es2015.17ccd8fa6555bc5cae50.js",
        "/default~Garako~index-es5.17ccd8fa6555bc5cae50.js",
        "/default~GurpsFW~index-es2015.34ba46f3863e1d46e873.js",
        "/default~GurpsFW~index-es5.34ba46f3863e1d46e873.js",
        "/default~HatsuneMiku~index-es2015.be498ffad53ba2180c2a.js",
        "/default~HatsuneMiku~index-es5.be498ffad53ba2180c2a.js",
        "/default~HuntersMoon~index-es2015.0dcebbb7d907a09d7e41.js",
        "/default~HuntersMoon~index-es5.0dcebbb7d907a09d7e41.js",
        "/default~InfiniteBabeL~index-es2015.65e2a921e229a535ec50.js",
        "/default~InfiniteBabeL~index-es5.65e2a921e229a535ec50.js",
        "/default~JekyllAndHyde~index-es2015.3625700799411db82b14.js",
        "/default~JekyllAndHyde~index-es5.3625700799411db82b14.js",
        "/default~KanColle~index-es2015.6514369b5766f27eadfb.js",
        "/default~KanColle~index-es5.6514369b5766f27eadfb.js",
        "/default~KillDeathBusiness_Korean~index-es2015.6a4ccd42a669648cd5ed.js",
        "/default~KillDeathBusiness_Korean~index-es5.6a4ccd42a669648cd5ed.js",
        "/default~LiveraDoll~index-es2015.2e4e38da0f671e55b4f0.js",
        "/default~LiveraDoll~index-es5.2e4e38da0f671e55b4f0.js",
        "/default~LogHorizon_Korean~index-es2015.1c1e479ddb51e1d0e310.js",
        "/default~LogHorizon_Korean~index-es5.1c1e479ddb51e1d0e310.js",
        "/default~LogHorizon~index-es2015.b955290a6fa96be4f50b.js",
        "/default~LogHorizon~index-es5.b955290a6fa96be4f50b.js",
        "/default~MagicaLogia_Korean~index-es2015.22b083655f95970c99cd.js",
        "/default~MagicaLogia_Korean~index-es5.22b083655f95970c99cd.js",
        "/default~MagicaLogia_SimplifiedChinese~index-es2015.f2a4e4ca082c30637350.js",
        "/default~MagicaLogia_SimplifiedChinese~index-es5.f2a4e4ca082c30637350.js",
        "/default~MagicaLogia~index-es2015.31c0b38a05dd018dfbb7.js",
        "/default~MagicaLogia~index-es5.31c0b38a05dd018dfbb7.js",
        "/default~MeikyuDays~index-es2015.fbdd82fe9b1fef64165a.js",
        "/default~MeikyuDays~index-es5.fbdd82fe9b1fef64165a.js",
        "/default~MeikyuKingdomBasic~index-es2015.de6d946e008d450a2ebd.js",
        "/default~MeikyuKingdomBasic~index-es5.de6d946e008d450a2ebd.js",
        "/default~MeikyuKingdom~index-es2015.10706d48870ce3d8d810.js",
        "/default~MeikyuKingdom~index-es5.10706d48870ce3d8d810.js",
        "/default~MetalHeadExtream~index-es2015.3045331b20fd8614500d.js",
        "/default~MetalHeadExtream~index-es5.3045331b20fd8614500d.js",
        "/default~NeverCloud~index-es2015.6f12589ca732079aa27c.js",
        "/default~NeverCloud~index-es5.6f12589ca732079aa27c.js",
        "/default~NinjaSlayer~index-es2015.a534a538a5ab3588bb11.js",
        "/default~NinjaSlayer~index-es5.a534a538a5ab3588bb11.js",
        "/default~OneWayHeroics~index-es2015.59b4ee0244262758ac35.js",
        "/default~OneWayHeroics~index-es5.59b4ee0244262758ac35.js",
        "/default~Paradiso~index-es2015.8e529859f2fe8e6c9309.js",
        "/default~Paradiso~index-es5.8e529859f2fe8e6c9309.js",
        "/default~ParasiteBlood~index-es2015.77da9c9e98c178df9c6c.js",
        "/default~ParasiteBlood~index-es5.77da9c9e98c178df9c6c.js",
        "/default~PulpCthulhu~index-es2015.4d288315c05a4ada111e.js",
        "/default~PulpCthulhu~index-es5.4d288315c05a4ada111e.js",
        "/default~RuinBreakers~index-es2015.aee5143936999d48c664.js",
        "/default~RuinBreakers~index-es5.aee5143936999d48c664.js",
        "/default~SamsaraBallad~index-es2015.1a8bcf724d219519065c.js",
        "/default~SamsaraBallad~index-es5.1a8bcf724d219519065c.js",
        "/default~Satasupe~index-es2015.1339e683a9d5ca022891.js",
        "/default~Satasupe~index-es5.1339e683a9d5ca022891.js",
        "/default~ScreamHighSchool~index-es2015.752d5ae11ceca232f651.js",
        "/default~ScreamHighSchool~index-es5.752d5ae11ceca232f651.js",
        "/default~ShinkuuGakuen~index-es2015.a22d4443a9c4eee656d1.js",
        "/default~ShinkuuGakuen~index-es5.a22d4443a9c4eee656d1.js",
        "/default~ShinobiGami~index-es2015.3ae6794cd518e6e72420.js",
        "/default~ShinobiGami~index-es5.3ae6794cd518e6e72420.js",
        "/default~ShoujoTenrankai~index-es2015.bf295b8a90d2c698339e.js",
        "/default~ShoujoTenrankai~index-es5.bf295b8a90d2c698339e.js",
        "/default~StarryDolls~index-es2015.fa1aa0697b5c9a62e93f.js",
        "/default~StarryDolls~index-es5.fa1aa0697b5c9a62e93f.js",
        "/default~SteamPunkers~index-es2015.238cb2078af92b548b85.js",
        "/default~SteamPunkers~index-es5.238cb2078af92b548b85.js",
        "/default~SterileLife~index-es2015.0026cb2e50c5d5cd87b6.js",
        "/default~SterileLife~index-es5.0026cb2e50c5d5cd87b6.js",
        "/default~SwordWorld2_0~index-es2015.da94abcae7ce6b1ce36c.js",
        "/default~SwordWorld2_0~index-es5.da94abcae7ce6b1ce36c.js",
        "/default~SwordWorld2_5~index-es2015.d3c0972c3c0acc5a1cfd.js",
        "/default~SwordWorld2_5~index-es5.d3c0972c3c0acc5a1cfd.js",
        "/default~SwordWorld~index-es2015.cd6bd0d45b18a2a451b3.js",
        "/default~SwordWorld~index-es5.cd6bd0d45b18a2a451b3.js",
        "/default~TwilightGunsmoke~index-es2015.565a4f1eacb6b7ecfcb4.js",
        "/default~TwilightGunsmoke~index-es5.565a4f1eacb6b7ecfcb4.js",
        "/default~UnsungDuet~index-es2015.0ad8a39adef332cbd7ac.js",
        "/default~UnsungDuet~index-es5.0ad8a39adef332cbd7ac.js",
        "/default~Villaciel~index-es2015.6b5473a1c4b56cf43e1d.js",
        "/default~Villaciel~index-es5.6b5473a1c4b56cf43e1d.js",
        "/default~Yggdrasill~index-es2015.3a977f307932b9d3bf90.js",
        "/default~Yggdrasill~index-es5.3a977f307932b9d3bf90.js",
        "/default~ZettaiReido~index-es2015.8879daf92e1388110a8c.js",
        "/default~ZettaiReido~index-es5.8879daf92e1388110a8c.js",
        "/favicon.ico",
        "/index-es2015.646f52b092930fc37cfc.js",
        "/index-es5.646f52b092930fc37cfc.js",
        "/index.html",
        "/main-es2015.059f5c3a64225a277bf8.js",
        "/main-es5.059f5c3a64225a277bf8.js",
        "/manifest.webmanifest",
        "/polyfills-es2015.44e87f6129a4288047f5.js",
        "/polyfills-es5.bf7e2fc3be6087042749.js",
        "/runtime-es2015.5f4baccca0a1c4e6cf19.js",
        "/runtime-es5.5f4baccca0a1c4e6cf19.js",
        "/styles.280e991c5992f8630bc9.css"
      ],
      "patterns": []
    },
    {
      "name": "assets",
      "installMode": "lazy",
      "updateMode": "prefetch",
      "cacheQueryOptions": {
        "ignoreVary": true
      },
      "urls": [
        "/assets/.htaccess",
        "/assets/config.yaml",
        "/assets/icons/icon-128x128.png",
        "/assets/icons/icon-144x144.png",
        "/assets/icons/icon-152x152.png",
        "/assets/icons/icon-192x192.png",
        "/assets/icons/icon-384x384.png",
        "/assets/icons/icon-512x512.png",
        "/assets/icons/icon-72x72.png",
        "/assets/icons/icon-96x96.png",
        "/assets/images/BG10a_80.jpg",
        "/assets/images/copyright.txt",
        "/assets/images/dice/100_dice/100_dice[100].png",
        "/assets/images/dice/100_dice/100_dice[10].png",
        "/assets/images/dice/100_dice/100_dice[20].png",
        "/assets/images/dice/100_dice/100_dice[30].png",
        "/assets/images/dice/100_dice/100_dice[40].png",
        "/assets/images/dice/100_dice/100_dice[50].png",
        "/assets/images/dice/100_dice/100_dice[60].png",
        "/assets/images/dice/100_dice/100_dice[70].png",
        "/assets/images/dice/100_dice/100_dice[80].png",
        "/assets/images/dice/100_dice/100_dice[90].png",
        "/assets/images/dice/10_dice/10_dice[10].png",
        "/assets/images/dice/10_dice/10_dice[1].png",
        "/assets/images/dice/10_dice/10_dice[2].png",
        "/assets/images/dice/10_dice/10_dice[3].png",
        "/assets/images/dice/10_dice/10_dice[4].png",
        "/assets/images/dice/10_dice/10_dice[5].png",
        "/assets/images/dice/10_dice/10_dice[6].png",
        "/assets/images/dice/10_dice/10_dice[7].png",
        "/assets/images/dice/10_dice/10_dice[8].png",
        "/assets/images/dice/10_dice/10_dice[9].png",
        "/assets/images/dice/12_dice/12_dice[10].png",
        "/assets/images/dice/12_dice/12_dice[11].png",
        "/assets/images/dice/12_dice/12_dice[12].png",
        "/assets/images/dice/12_dice/12_dice[1].png",
        "/assets/images/dice/12_dice/12_dice[2].png",
        "/assets/images/dice/12_dice/12_dice[3].png",
        "/assets/images/dice/12_dice/12_dice[4].png",
        "/assets/images/dice/12_dice/12_dice[5].png",
        "/assets/images/dice/12_dice/12_dice[6].png",
        "/assets/images/dice/12_dice/12_dice[7].png",
        "/assets/images/dice/12_dice/12_dice[8].png",
        "/assets/images/dice/12_dice/12_dice[9].png",
        "/assets/images/dice/20_dice/20_dice[0].png",
        "/assets/images/dice/20_dice/20_dice[10].png",
        "/assets/images/dice/20_dice/20_dice[11].png",
        "/assets/images/dice/20_dice/20_dice[12].png",
        "/assets/images/dice/20_dice/20_dice[13].png",
        "/assets/images/dice/20_dice/20_dice[14].png",
        "/assets/images/dice/20_dice/20_dice[15].png",
        "/assets/images/dice/20_dice/20_dice[16].png",
        "/assets/images/dice/20_dice/20_dice[17].png",
        "/assets/images/dice/20_dice/20_dice[18].png",
        "/assets/images/dice/20_dice/20_dice[19].png",
        "/assets/images/dice/20_dice/20_dice[1].png",
        "/assets/images/dice/20_dice/20_dice[20].png",
        "/assets/images/dice/20_dice/20_dice[2].png",
        "/assets/images/dice/20_dice/20_dice[3].png",
        "/assets/images/dice/20_dice/20_dice[4].png",
        "/assets/images/dice/20_dice/20_dice[5].png",
        "/assets/images/dice/20_dice/20_dice[6].png",
        "/assets/images/dice/20_dice/20_dice[7].png",
        "/assets/images/dice/20_dice/20_dice[8].png",
        "/assets/images/dice/20_dice/20_dice[9].png",
        "/assets/images/dice/2_coin/2_coin[表].png",
        "/assets/images/dice/2_coin/2_coin[裏].png",
        "/assets/images/dice/4_dice/4_dice[1].png",
        "/assets/images/dice/4_dice/4_dice[2].png",
        "/assets/images/dice/4_dice/4_dice[3].png",
        "/assets/images/dice/4_dice/4_dice[4].png",
        "/assets/images/dice/6_dice/6_dice[0].png",
        "/assets/images/dice/6_dice/6_dice[1].png",
        "/assets/images/dice/6_dice/6_dice[2].png",
        "/assets/images/dice/6_dice/6_dice[3].png",
        "/assets/images/dice/6_dice/6_dice[4].png",
        "/assets/images/dice/6_dice/6_dice[5].png",
        "/assets/images/dice/6_dice/6_dice[6].png",
        "/assets/images/dice/6_dice_black/6_dice_black[0].png",
        "/assets/images/dice/6_dice_black/6_dice_black[1].png",
        "/assets/images/dice/6_dice_black/6_dice_black[2].png",
        "/assets/images/dice/6_dice_black/6_dice_black[3].png",
        "/assets/images/dice/6_dice_black/6_dice_black[4].png",
        "/assets/images/dice/6_dice_black/6_dice_black[5].png",
        "/assets/images/dice/6_dice_black/6_dice_black[6].png",
        "/assets/images/dice/8_dice/8_dice[1].png",
        "/assets/images/dice/8_dice/8_dice[2].png",
        "/assets/images/dice/8_dice/8_dice[3].png",
        "/assets/images/dice/8_dice/8_dice[4].png",
        "/assets/images/dice/8_dice/8_dice[5].png",
        "/assets/images/dice/8_dice/8_dice[6].png",
        "/assets/images/dice/8_dice/8_dice[7].png",
        "/assets/images/dice/8_dice/8_dice[8].png",
        "/assets/images/dice/license.txt",
        "/assets/images/ic_account_circle_black_24dp_2x.png",
        "/assets/images/loading.gif",
        "/assets/images/mon_052.gif",
        "/assets/images/mon_128.gif",
        "/assets/images/mon_135.gif",
        "/assets/images/mon_150.gif",
        "/assets/images/mon_211.gif",
        "/assets/images/nc96424.png",
        "/assets/images/skeleton.png",
        "/assets/images/tex.jpg",
        "/assets/images/trump/blank_card.png",
        "/assets/images/trump/c01.gif",
        "/assets/images/trump/c02.gif",
        "/assets/images/trump/c03.gif",
        "/assets/images/trump/c04.gif",
        "/assets/images/trump/c05.gif",
        "/assets/images/trump/c06.gif",
        "/assets/images/trump/c07.gif",
        "/assets/images/trump/c08.gif",
        "/assets/images/trump/c09.gif",
        "/assets/images/trump/c10.gif",
        "/assets/images/trump/c11.gif",
        "/assets/images/trump/c12.gif",
        "/assets/images/trump/c13.gif",
        "/assets/images/trump/d01.gif",
        "/assets/images/trump/d02.gif",
        "/assets/images/trump/d03.gif",
        "/assets/images/trump/d04.gif",
        "/assets/images/trump/d05.gif",
        "/assets/images/trump/d06.gif",
        "/assets/images/trump/d07.gif",
        "/assets/images/trump/d08.gif",
        "/assets/images/trump/d09.gif",
        "/assets/images/trump/d10.gif",
        "/assets/images/trump/d11.gif",
        "/assets/images/trump/d12.gif",
        "/assets/images/trump/d13.gif",
        "/assets/images/trump/h01.gif",
        "/assets/images/trump/h02.gif",
        "/assets/images/trump/h03.gif",
        "/assets/images/trump/h04.gif",
        "/assets/images/trump/h05.gif",
        "/assets/images/trump/h06.gif",
        "/assets/images/trump/h07.gif",
        "/assets/images/trump/h08.gif",
        "/assets/images/trump/h09.gif",
        "/assets/images/trump/h10.gif",
        "/assets/images/trump/h11.gif",
        "/assets/images/trump/h12.gif",
        "/assets/images/trump/h13.gif",
        "/assets/images/trump/s01.gif",
        "/assets/images/trump/s02.gif",
        "/assets/images/trump/s03.gif",
        "/assets/images/trump/s04.gif",
        "/assets/images/trump/s05.gif",
        "/assets/images/trump/s06.gif",
        "/assets/images/trump/s07.gif",
        "/assets/images/trump/s08.gif",
        "/assets/images/trump/s09.gif",
        "/assets/images/trump/s10.gif",
        "/assets/images/trump/s11.gif",
        "/assets/images/trump/s12.gif",
        "/assets/images/trump/s13.gif",
        "/assets/images/trump/x01.gif",
        "/assets/images/trump/x02.gif",
        "/assets/images/trump/z01.gif",
        "/assets/images/trump/z02.gif",
        "/assets/sounds/niconicomons/copyright.txt",
        "/assets/sounds/niconicomons/nc146227.mp3",
        "/assets/sounds/on-jin/copyright.txt",
        "/assets/sounds/on-jin/spo_ge_saikoro_teburu01.mp3",
        "/assets/sounds/on-jin/spo_ge_saikoro_teburu02.mp3",
        "/assets/sounds/otologic/Onmtp-Surprise02-1.mp3",
        "/assets/sounds/otologic/copyright.txt",
        "/assets/sounds/soundeffect-lab/book-stack1.mp3",
        "/assets/sounds/soundeffect-lab/card-open1.mp3",
        "/assets/sounds/soundeffect-lab/card-turn-over1.mp3",
        "/assets/sounds/soundeffect-lab/copyright.txt",
        "/assets/sounds/soundeffect-lab/puyon1.mp3",
        "/assets/sounds/soundeffect-lab/shoulder-touch1.mp3",
        "/assets/sounds/tm2/copyright.txt",
        "/assets/sounds/tm2/tm2_pon002.wav",
        "/assets/sounds/tm2/tm2_swing003.wav",
        "/assets/sounds/tm2/tm2_switch001.wav",
        "/assets/styles.css",
        "/card.png"
      ],
      "patterns": []
    }
  ],
  "dataGroups": [],
  "hashTable": {
    "/assets/.htaccess": "31a4651614d9ae730f1d414516823a37eed01be5",
    "/assets/config.yaml": "af8646f94fd72ed185ab2bb8c7cd1d8da3eb2687",
    "/assets/icons/icon-128x128.png": "441cfb3462dd382410ca129a73f4f10012ac53d6",
    "/assets/icons/icon-144x144.png": "515a6d7db344ac1f596233226882bd039f00069a",
    "/assets/icons/icon-152x152.png": "a4de1f39b82984368750f720682c4105c44592e8",
    "/assets/icons/icon-192x192.png": "13f8349ac4d100b72a6af595f63163caca63a3f3",
    "/assets/icons/icon-384x384.png": "70bad998fb57487b65d3311c9758e93b0f909ee6",
    "/assets/icons/icon-512x512.png": "c58755dfd9c5524a85eef6c9bffb059186d44bdb",
    "/assets/icons/icon-72x72.png": "35fca58b80ea64415d163f43268d3a93ca94c6db",
    "/assets/icons/icon-96x96.png": "a2974a288162815aa45691483f528fe8f2becb73",
    "/assets/images/BG10a_80.jpg": "46ec9f5a73d8de11a55fda1e011f855a1b14b100",
    "/assets/images/copyright.txt": "31b5ce0f0303822ca67d95492f01a96adf7dceac",
    "/assets/images/dice/100_dice/100_dice[100].png": "65300b4e3f43a0404a9ba83e656362639e6b4de6",
    "/assets/images/dice/100_dice/100_dice[10].png": "17f2cb6336fe1254b20faffbfa63395005ac8b4e",
    "/assets/images/dice/100_dice/100_dice[20].png": "3e78d068e3a782b216869b37e788ba751dea44de",
    "/assets/images/dice/100_dice/100_dice[30].png": "886fc7b960cd7a87da3ba1c7093d39a9ce6084b8",
    "/assets/images/dice/100_dice/100_dice[40].png": "047c6c6f415f89141a92897bf0025502624e634a",
    "/assets/images/dice/100_dice/100_dice[50].png": "a33b661b59063d305a58cc34b858606a8ff20f07",
    "/assets/images/dice/100_dice/100_dice[60].png": "bbe994b0ce2e50d55c44b8b91ed73aee20382f3d",
    "/assets/images/dice/100_dice/100_dice[70].png": "764cf119bcd6d1324c9a3ebcfc6a2159e96edf29",
    "/assets/images/dice/100_dice/100_dice[80].png": "73a9009b70c1364f5c90ff4ca25ae8c1a9fab49a",
    "/assets/images/dice/100_dice/100_dice[90].png": "7a41a696661e4e0a3d839faca44b6efac760ca23",
    "/assets/images/dice/10_dice/10_dice[10].png": "fc3d4eaf409c998cde87b38ece1188801b454e8b",
    "/assets/images/dice/10_dice/10_dice[1].png": "6542df4e26d1942a78a2abf238f96da61a87d6f5",
    "/assets/images/dice/10_dice/10_dice[2].png": "15f0ae961c7f542c0e413189f13f022b30f65d65",
    "/assets/images/dice/10_dice/10_dice[3].png": "2d43c10d486841b2948ff11a3a89cf71e3558dbc",
    "/assets/images/dice/10_dice/10_dice[4].png": "c2f89f33607b2950d89b312ce86b9808af0744bf",
    "/assets/images/dice/10_dice/10_dice[5].png": "ce6e05a67a1b0da70e14d92de68c0f69b59e878a",
    "/assets/images/dice/10_dice/10_dice[6].png": "86b96959a9574d685c01605440106c4590b0954b",
    "/assets/images/dice/10_dice/10_dice[7].png": "18e8ae866608eeb88f1fbc17837935fd800db52f",
    "/assets/images/dice/10_dice/10_dice[8].png": "aa3d93de64788d9b4fc49177bbc2243eb6775a6b",
    "/assets/images/dice/10_dice/10_dice[9].png": "3242b42072fc962f8e5ef16a46f20ab69488f84e",
    "/assets/images/dice/12_dice/12_dice[10].png": "549d781eaff4543c99caefda766e09b8d00fea3e",
    "/assets/images/dice/12_dice/12_dice[11].png": "2704b385b2818eb0252536195e7d72beb9d2723f",
    "/assets/images/dice/12_dice/12_dice[12].png": "56455223876a0ef4b9cfee9c5a3faee502806398",
    "/assets/images/dice/12_dice/12_dice[1].png": "a9a31332154505aa7ee038cd0362d31be8603ce3",
    "/assets/images/dice/12_dice/12_dice[2].png": "a65154fcbde00b712db6bea2b26bb057c7531a3c",
    "/assets/images/dice/12_dice/12_dice[3].png": "23252df625e1f8ad8d8265aaa5e56f1f30de4e88",
    "/assets/images/dice/12_dice/12_dice[4].png": "35b99802f480a7b9341c10d74e74f45bdd92f077",
    "/assets/images/dice/12_dice/12_dice[5].png": "8ca8df2a479e4967d111309730749028e34ca40d",
    "/assets/images/dice/12_dice/12_dice[6].png": "ba3593178dfaba659a80164d9ebfefe5513294d8",
    "/assets/images/dice/12_dice/12_dice[7].png": "648bce0303ab96d2a5a270c5b3a317f3e56e7d1c",
    "/assets/images/dice/12_dice/12_dice[8].png": "945fab267cc52544ff31878481925d56d87459c7",
    "/assets/images/dice/12_dice/12_dice[9].png": "98388a23d3ae8a75886a27e626097417ab819c51",
    "/assets/images/dice/20_dice/20_dice[0].png": "ad7ed44e121ead7633e9cf94fa1a292ce6203853",
    "/assets/images/dice/20_dice/20_dice[10].png": "9b14025af7eca8c85216cf018a450c8ae84c9366",
    "/assets/images/dice/20_dice/20_dice[11].png": "cf1f632f4d664ba3b5f1bd3f9fdddd1188d4de42",
    "/assets/images/dice/20_dice/20_dice[12].png": "8638a3b133e9342b09908d32e8227455e1dfa9da",
    "/assets/images/dice/20_dice/20_dice[13].png": "9374f98489f4872109250526504f362a7d3823bf",
    "/assets/images/dice/20_dice/20_dice[14].png": "6b00b13aa611d73b26d1b88043828e5bd0b6e2af",
    "/assets/images/dice/20_dice/20_dice[15].png": "4ef4391d00755dbd0e754644f5c3637c3c404ddd",
    "/assets/images/dice/20_dice/20_dice[16].png": "6fa0f90d7a124586059fd0230cb12b8507cd35ae",
    "/assets/images/dice/20_dice/20_dice[17].png": "51e0be999a740ea64a7bfbd7cc0ba3c326c087cd",
    "/assets/images/dice/20_dice/20_dice[18].png": "00e3ffe118e499bddb2cb70d3fe06fae5aeca0fa",
    "/assets/images/dice/20_dice/20_dice[19].png": "986916ff852c6e5ae6b5fed08e5740de8ad5ba1d",
    "/assets/images/dice/20_dice/20_dice[1].png": "be8244cd004ce54b2b2b19606f0a2f7d5ba2feba",
    "/assets/images/dice/20_dice/20_dice[20].png": "402f13937d523cb9ac33e885167d2e4557f68ec9",
    "/assets/images/dice/20_dice/20_dice[2].png": "cd8fe9511902bfc28b09296b117e92a84171adcc",
    "/assets/images/dice/20_dice/20_dice[3].png": "2c43aba8cb480906e01708588cda66261db432cf",
    "/assets/images/dice/20_dice/20_dice[4].png": "5af671ed487a178965c34286e29d4316a3fe2bd6",
    "/assets/images/dice/20_dice/20_dice[5].png": "5fbefe58b59d24aed4170b709e4735ad27aa031a",
    "/assets/images/dice/20_dice/20_dice[6].png": "0d61b2efc002c5f3c69babdce82d03316e809cf2",
    "/assets/images/dice/20_dice/20_dice[7].png": "cc28f465d375919f49f43897594b634c9eb6661f",
    "/assets/images/dice/20_dice/20_dice[8].png": "a95828c1b26e17843033c4aa25c4a42e58ed7bc6",
    "/assets/images/dice/20_dice/20_dice[9].png": "8b028c682e49cee41e7fa3c8b9352542def3eb34",
    "/assets/images/dice/2_coin/2_coin[表].png": "3b78e01477a15a6a510fa4802bd347bae7684b29",
    "/assets/images/dice/2_coin/2_coin[裏].png": "6cf5106df3cadab8c6ac452e01195c05d0f6e130",
    "/assets/images/dice/4_dice/4_dice[1].png": "96c41b60a4c80f7e04b28f1e691c90ad991bded0",
    "/assets/images/dice/4_dice/4_dice[2].png": "a1e82e922614e15be8c1c5b17e975a072a8a1724",
    "/assets/images/dice/4_dice/4_dice[3].png": "8778049ed2dc59546eafd10c19467fef1538a8e0",
    "/assets/images/dice/4_dice/4_dice[4].png": "d6da698b738a6041957ccdd55c09fbd6f0e7e267",
    "/assets/images/dice/6_dice/6_dice[0].png": "716a0128f6a2765e6c782e4a96db2dbbfb1ad34e",
    "/assets/images/dice/6_dice/6_dice[1].png": "54f6185acf50f846d379c48170bebbadd95e06fd",
    "/assets/images/dice/6_dice/6_dice[2].png": "a2e8d73202fedd7a1f187e6b7e775ab1b63f1d9c",
    "/assets/images/dice/6_dice/6_dice[3].png": "0b68c8117719279b28bfce29bf6ec5adbb34751e",
    "/assets/images/dice/6_dice/6_dice[4].png": "23bb1da2bc86c5a339156d454b9c50d884785859",
    "/assets/images/dice/6_dice/6_dice[5].png": "c388719773193bbead654f93cf2c8cd2ef0edec2",
    "/assets/images/dice/6_dice/6_dice[6].png": "1f0cfe7ffbf384a55ac59558ded71259d100ba7c",
    "/assets/images/dice/6_dice_black/6_dice_black[0].png": "a74218817c154b2f1d4284939bfed8634e690450",
    "/assets/images/dice/6_dice_black/6_dice_black[1].png": "7fbbeb3ea6f2ceb181d235f066d73e6dc25ac41b",
    "/assets/images/dice/6_dice_black/6_dice_black[2].png": "d1c9ca51f6b7e06d0477f7cdb39fa84cde17a5a7",
    "/assets/images/dice/6_dice_black/6_dice_black[3].png": "9793618bf2545b2316d8de0d62659709fed397ad",
    "/assets/images/dice/6_dice_black/6_dice_black[4].png": "dc50e1accd4fc758f80b9735b36ba3efac6f41f4",
    "/assets/images/dice/6_dice_black/6_dice_black[5].png": "7e78b793403e7c2a27372e0fc0c7eca9ec505454",
    "/assets/images/dice/6_dice_black/6_dice_black[6].png": "cec9f7dff90da68b7fc13c9e39bd1422d201a034",
    "/assets/images/dice/8_dice/8_dice[1].png": "2cb15e8ca832eee1a99c380ed784573c1775fd08",
    "/assets/images/dice/8_dice/8_dice[2].png": "c594afdf5b78000b0dd18f5c46eca813ad3763d8",
    "/assets/images/dice/8_dice/8_dice[3].png": "e77f81d2b522105d3661cc587ad0a0d32b81333e",
    "/assets/images/dice/8_dice/8_dice[4].png": "88ddcee6baa174e68abb61598b3e9b4ed1f433a6",
    "/assets/images/dice/8_dice/8_dice[5].png": "18b190d5fe4a7ded9184f4a657f1db02e509bed5",
    "/assets/images/dice/8_dice/8_dice[6].png": "d81533f9eda42e04f043a35a72265461a19a2764",
    "/assets/images/dice/8_dice/8_dice[7].png": "ee5d16a6ea66eeb1e8e52c61bc4c57240e82851d",
    "/assets/images/dice/8_dice/8_dice[8].png": "5a2a2a3e4aed1de46045e6b64f797510fac4c817",
    "/assets/images/dice/license.txt": "1f23c47526a98e1bd9d1af8f494bfe3bb50e4e45",
    "/assets/images/ic_account_circle_black_24dp_2x.png": "c3726dff18b287ab234094a4253de8e76cfe5fd8",
    "/assets/images/loading.gif": "0071e4ff0d9b516e32af62ec5f9d9389c01d0aea",
    "/assets/images/mon_052.gif": "6e6cbffa21503f0d2e00770e9d5e867f7d681628",
    "/assets/images/mon_128.gif": "cda4bb64ee30ba67424c47c116afa1761eaa6c0a",
    "/assets/images/mon_135.gif": "30252e78d26bf31ae42c6c3b51ab1fb543d63d7b",
    "/assets/images/mon_150.gif": "5032fef9447a5c47cba11cb05d534986461521b6",
    "/assets/images/mon_211.gif": "8cbd9fac93238d86c5688505730b7fa403428cfb",
    "/assets/images/nc96424.png": "7ac12279b965ea51b301ef003d7e301e9a9b5510",
    "/assets/images/skeleton.png": "9b875b7b5dd70a6556847c93e520b40fbc865e01",
    "/assets/images/tex.jpg": "eb3117f2c21d0e72882031418d5a9d7417f4f1b4",
    "/assets/images/trump/blank_card.png": "3d6af7db4d320a299424343bbd3db3b5b052a99b",
    "/assets/images/trump/c01.gif": "0aa75276941e1ba6ebf16370c442b4d9bfe034bd",
    "/assets/images/trump/c02.gif": "6228511ddacac9fd6e6ea255778579e639829e5b",
    "/assets/images/trump/c03.gif": "0886923275d306be4de88ca61c3af8ce64a14424",
    "/assets/images/trump/c04.gif": "6bce49c683e7611b42132ab64bdf916f673b7d45",
    "/assets/images/trump/c05.gif": "cd70163df56345494d41426b0bc701d9c5d66045",
    "/assets/images/trump/c06.gif": "2153645a38e54bf822a7d23c3247ed66d7595d7b",
    "/assets/images/trump/c07.gif": "8916b5e6ef3608a7c52168064d7be284b7218c4c",
    "/assets/images/trump/c08.gif": "98adaa76d2b95f15883188f24112b57ad69dfa3e",
    "/assets/images/trump/c09.gif": "f8815799f2b238fb0a819cfcf4e54e27c524223b",
    "/assets/images/trump/c10.gif": "1b6b7a1b58639a7d903c4a6406d39e49c593d520",
    "/assets/images/trump/c11.gif": "3a741861283fc7a1369ece409e6e97688de0d61f",
    "/assets/images/trump/c12.gif": "d24238004e2fb618dbf676a8f43d385b87c3122b",
    "/assets/images/trump/c13.gif": "c82f0cce4c19634b6402f752f1d53f1a5858577a",
    "/assets/images/trump/d01.gif": "f5d9b821ea1cc306955f66c20c5f00809fe05332",
    "/assets/images/trump/d02.gif": "739486a34ad3892a93e9a5d053f71cb231c68417",
    "/assets/images/trump/d03.gif": "80cc494fc44fc835c77d42dfa872e7d9a7240c92",
    "/assets/images/trump/d04.gif": "f11f3795c1586ac6bf7953098fa1cf2cc070e04b",
    "/assets/images/trump/d05.gif": "d6cc2e096e10605a8ecdb154ce8bdc16731652cb",
    "/assets/images/trump/d06.gif": "0b735ac34ff5cca93256be319570977054bda525",
    "/assets/images/trump/d07.gif": "062c3dd25a52230fa58243383aa2305b6034ec0e",
    "/assets/images/trump/d08.gif": "3e1c71d77591a36d549ce51c25a05ffeff5af368",
    "/assets/images/trump/d09.gif": "02956fcf8fd5a8a6b97d5bdfe3540a0d74301ca2",
    "/assets/images/trump/d10.gif": "99e78bf0486c164801de6547f49db4a336f413bf",
    "/assets/images/trump/d11.gif": "6b5107a6ea7f13689b412a1578f40b9e62013b88",
    "/assets/images/trump/d12.gif": "682866e8ff8b0683610caaac9f0762b2e4128585",
    "/assets/images/trump/d13.gif": "b9514224482c2b4a0fa54d39570bf6b204ab2daf",
    "/assets/images/trump/h01.gif": "d0c3a78bf268facdd818a793bd4499de48a15772",
    "/assets/images/trump/h02.gif": "ddab0cac080a43e1778e0921df0f1ff8e0a4f315",
    "/assets/images/trump/h03.gif": "36f77dbfe5610bcc54e1a2a8c657b8719cc0aa67",
    "/assets/images/trump/h04.gif": "d943be1d8e5db4a9cc39e1c13b90c72e8bd3d3f1",
    "/assets/images/trump/h05.gif": "143d404a5ce36c4abc6d30e0eebef4b11fd937ac",
    "/assets/images/trump/h06.gif": "7777492fcac42d7e09a3c2a136883d6b9cf31a66",
    "/assets/images/trump/h07.gif": "c00de434933b0c0e54b137e02a329b856d95b3a4",
    "/assets/images/trump/h08.gif": "32ea5ce937f5c369d8e615417e8494f7d0131651",
    "/assets/images/trump/h09.gif": "c2f71458ad9a659f1ed4d14c2926d5a4b664b341",
    "/assets/images/trump/h10.gif": "eb5704ca4b59cdac96c6739143b0c76e6d61c634",
    "/assets/images/trump/h11.gif": "7756de251029df4171f2ddbb089d8a279cad1e6c",
    "/assets/images/trump/h12.gif": "eda6c6685b80eec8b6e54ecfdaec0752f508d689",
    "/assets/images/trump/h13.gif": "8b406189f542a5cb0253736691750243c9fe0e43",
    "/assets/images/trump/s01.gif": "74419a95087f602e4b4634c5bb24f2dcee9284fa",
    "/assets/images/trump/s02.gif": "3d36b421b0772986a79f2680ab6e3db6e47ec22c",
    "/assets/images/trump/s03.gif": "54a3efb858cc4bbccf83b719f8b596fd8d932825",
    "/assets/images/trump/s04.gif": "d79e93ec29bb51b4e5f2f310e35577c01cdeaec8",
    "/assets/images/trump/s05.gif": "1482e1d453a0c776f1402ef98d644b2ab00f68c3",
    "/assets/images/trump/s06.gif": "37e9f8743b6d6438134c59e7b57758787f811fbd",
    "/assets/images/trump/s07.gif": "66fdedc9cd4cae1863bd046355592aaf1e3716b3",
    "/assets/images/trump/s08.gif": "c0a0afc6026c32ba25c3f680b99639de64e91da8",
    "/assets/images/trump/s09.gif": "e4237a16ceb2e848ced2f25e7e6971cb78d1dd22",
    "/assets/images/trump/s10.gif": "10929f6509e203430c59133dde8ca40ffe87fee7",
    "/assets/images/trump/s11.gif": "139a32d96e8beda4dcf1679ef8d778526799c8b7",
    "/assets/images/trump/s12.gif": "040eca5caec9bcb175222d58c322879a79caf5f3",
    "/assets/images/trump/s13.gif": "bf7d87e30a001934f509c206bbecd167de2857b8",
    "/assets/images/trump/x01.gif": "c5cdc275cee82c777bafa7e779a1ad6536cb88c1",
    "/assets/images/trump/x02.gif": "a16c84e34f9b4d32fba3f9bb58edf6cb78a3710c",
    "/assets/images/trump/z01.gif": "09ec5763f5c542d77cfa192d52caef24cce3c459",
    "/assets/images/trump/z02.gif": "e6f2b3d1e42af867b62f8d5f63491cd20018f05b",
    "/assets/sounds/niconicomons/copyright.txt": "eabb56fd7871a1f27e04602de08c3c77e086203e",
    "/assets/sounds/niconicomons/nc146227.mp3": "377b77c0d18a53f2ca5de1f409471af8c7f5089c",
    "/assets/sounds/on-jin/copyright.txt": "d18bf161a83ff08ea1887c914f59b26a2f6151bd",
    "/assets/sounds/on-jin/spo_ge_saikoro_teburu01.mp3": "322db28e9974b121aece445a166858a294920d86",
    "/assets/sounds/on-jin/spo_ge_saikoro_teburu02.mp3": "6e416f3fa21086aa8cb64bee30ebd134c3e09187",
    "/assets/sounds/otologic/Onmtp-Surprise02-1.mp3": "1e961a6c87a8454ae85911b78cc6420a38bc6ff9",
    "/assets/sounds/otologic/copyright.txt": "eea893bc50381f77f2f57da2cf17b55e4a537c1a",
    "/assets/sounds/soundeffect-lab/book-stack1.mp3": "bd9d64881784acb3f9d35e67f18f0dd3716b6eed",
    "/assets/sounds/soundeffect-lab/card-open1.mp3": "6dc11cfb3f560abfe72476fbb6cc61f3a7ab43f0",
    "/assets/sounds/soundeffect-lab/card-turn-over1.mp3": "6f98ef53f10652bc5be5eedec1e6431cbf04da66",
    "/assets/sounds/soundeffect-lab/copyright.txt": "3e651b37ed569832f3162dd02cb058c47940c4df",
    "/assets/sounds/soundeffect-lab/puyon1.mp3": "7b268d35cf1c2236bd7de2b9f884b286d36fbe0a",
    "/assets/sounds/soundeffect-lab/shoulder-touch1.mp3": "8f5df7419b61c6f079d2b3796f9e1877e89ef74f",
    "/assets/sounds/tm2/copyright.txt": "d1746526d6033ed9ed762e76f009386c06b52722",
    "/assets/sounds/tm2/tm2_pon002.wav": "18f7714c0c9b9b317865a6c2ed1364ba644ee97f",
    "/assets/sounds/tm2/tm2_swing003.wav": "c90ac458f22fcfab9b3d6c2ec9affd08f05e1d3f",
    "/assets/sounds/tm2/tm2_switch001.wav": "9d24b56a2ee54a41910341caf0b1bce4fdc6e99a",
    "/assets/styles.css": "9b259434eb588448b7871da7404176f7c41c2e92",
    "/card.png": "f50b1df499e37466ad70e32e0496fb1792466dc7",
    "/common-es2015.a3af4c990831a830edd0.js": "43fb20ec769d364e241c9c29de6677f3696d7390",
    "/common-es5.a3af4c990831a830edd0.js": "65d9a3496d26d13d6cc8d75135a6f269fd94d119",
    "/default~AlchemiaStruggle~index-es2015.0224f6625aedc30e083f.js": "6916fe808cbd902ce4dd3fc1d2e459a6d61b149b",
    "/default~AlchemiaStruggle~index-es5.0224f6625aedc30e083f.js": "1ab66c3013e320de07021e09017ae65ecc6f6942",
    "/default~AngelGear~index-es2015.4459dfea6bfa2b9ff8b2.js": "cc75703d642789821d754d88cfe04753d0ce4fde",
    "/default~AngelGear~index-es5.4459dfea6bfa2b9ff8b2.js": "cc75703d642789821d754d88cfe04753d0ce4fde",
    "/default~AnimaAnimus~index-es2015.9bca9ed50b1b0f200891.js": "0fb60b47d03e94b85abe2018703cd8c1f2cfc3ef",
    "/default~AnimaAnimus~index-es5.9bca9ed50b1b0f200891.js": "2c61f64c2a9bec45da2cb18f9dcc4e564940c8bc",
    "/default~BattleTech~index-es2015.6fa618469cd2ddaf67cb.js": "476643e59a6269ee2f28e1611befbe185334d86b",
    "/default~BattleTech~index-es5.6fa618469cd2ddaf67cb.js": "df0ce7dddeaa9ec82eac181518f05a5de2f25a64",
    "/default~BeginningIdol_Korean~index-es2015.322c54b2b7565e07da4e.js": "10cd4aad2cf7625c3eec478dfb16929006a13211",
    "/default~BeginningIdol_Korean~index-es5.322c54b2b7565e07da4e.js": "10cd4aad2cf7625c3eec478dfb16929006a13211",
    "/default~BeginningIdol~index-es2015.07bb12b4845fe6f5a77f.js": "9f851b5742d0b446479ecf4f197b313f4f5f46da",
    "/default~BeginningIdol~index-es5.07bb12b4845fe6f5a77f.js": "9f851b5742d0b446479ecf4f197b313f4f5f46da",
    "/default~BlindMythos~index-es2015.6587af6166e7e8380683.js": "28dcbbc23054c5f81227b7543440524ffe248c69",
    "/default~BlindMythos~index-es5.6587af6166e7e8380683.js": "28dcbbc23054c5f81227b7543440524ffe248c69",
    "/default~BloodCrusade~index-es2015.aee75fb0df01bc4c6149.js": "6aa9038d9e00759ec9bff4ffd903ae9fe333a9a6",
    "/default~BloodCrusade~index-es5.aee75fb0df01bc4c6149.js": "6aa9038d9e00759ec9bff4ffd903ae9fe333a9a6",
    "/default~BloodMoon~index-es2015.2423cc88233b62554acb.js": "3f55e7fe4468ecba1a7e8556992ae478140cd13d",
    "/default~BloodMoon~index-es5.2423cc88233b62554acb.js": "3f55e7fe4468ecba1a7e8556992ae478140cd13d",
    "/default~ColossalHunter~index-es2015.732e36f2db14d4e675e2.js": "072505627841a6de321ffb376ad0484ee1b68ca1",
    "/default~ColossalHunter~index-es5.732e36f2db14d4e675e2.js": "072505627841a6de321ffb376ad0484ee1b68ca1",
    "/default~Cthulhu7th~index-es2015.15f1bfc4e4859f67881d.js": "763673da8bb5058d09746f75aee505128e0e0807",
    "/default~Cthulhu7th~index-es5.15f1bfc4e4859f67881d.js": "763673da8bb5058d09746f75aee505128e0e0807",
    "/default~DeadlineHeroes~index-es2015.02c25655b2808f8d12f1.js": "d5ffa793ce4422031989175079702c039ed9ac21",
    "/default~DeadlineHeroes~index-es5.02c25655b2808f8d12f1.js": "a409c36e6c877d926a842ba958bb901740d2e657",
    "/default~DemonParasite~index-es2015.e6ae355451aaf002e076.js": "74d7819cd8dea5167fb5085ee29fd960561ed127",
    "/default~DemonParasite~index-es5.e6ae355451aaf002e076.js": "74d7819cd8dea5167fb5085ee29fd960561ed127",
    "/default~DesperateRun~index-es2015.1678bf80fb05d5414fb5.js": "5365e6c509db26a3bd0617126c63f10f48a2f55b",
    "/default~DesperateRun~index-es5.1678bf80fb05d5414fb5.js": "aedd8a16f0f9ed787ab8433aea8c01b77904da8b",
    "/default~DoubleCross_Korean~index-es2015.8f61f652e1412d02ed5d.js": "8c0f47bd3e779d4d9f8d858a8107ede4afc47401",
    "/default~DoubleCross_Korean~index-es5.8f61f652e1412d02ed5d.js": "869d61bd573fa3d322ea196bb6b16631ca1b8ae7",
    "/default~DoubleCross~index-es2015.83a393c976d3c5f78138.js": "db876003e02075605950ba53feab34b7a74ca171",
    "/default~DoubleCross~index-es5.83a393c976d3c5f78138.js": "ddde354f2a9d527c5939b83eacbafb7c8b474515",
    "/default~Elysion~index-es2015.38bc3763bd949da1ab5e.js": "b535665c77dbf273594c08f6f560928695e5c44b",
    "/default~Elysion~index-es5.38bc3763bd949da1ab5e.js": "b535665c77dbf273594c08f6f560928695e5c44b",
    "/default~FilledWith~index-es2015.fa9e9699e9e0d95f2ba9.js": "257b4c95592828dc87643827148611ac6af2ba27",
    "/default~FilledWith~index-es5.fa9e9699e9e0d95f2ba9.js": "54df0db73fb1a86a91b4f5fccb8f33da7afe90d9",
    "/default~Garako~index-es2015.17ccd8fa6555bc5cae50.js": "16e0ecd82c2884dbf0cee95169868cd7ab94cb2b",
    "/default~Garako~index-es5.17ccd8fa6555bc5cae50.js": "42f15771c0ab25aedc50730b1c2f53ca7769426f",
    "/default~GurpsFW~index-es2015.34ba46f3863e1d46e873.js": "49661f1106c289c920fae0fbe94eefcac8ff3206",
    "/default~GurpsFW~index-es5.34ba46f3863e1d46e873.js": "cbf8f07429e5f5ece029667b6bbf71437e95c79d",
    "/default~HatsuneMiku~index-es2015.be498ffad53ba2180c2a.js": "a3536e34d363ef577ac8c115d58b184425ea7c9f",
    "/default~HatsuneMiku~index-es5.be498ffad53ba2180c2a.js": "a3536e34d363ef577ac8c115d58b184425ea7c9f",
    "/default~HuntersMoon~index-es2015.0dcebbb7d907a09d7e41.js": "b21ee5a7d712a0a6d2da394d00175acaeb63758d",
    "/default~HuntersMoon~index-es5.0dcebbb7d907a09d7e41.js": "b21ee5a7d712a0a6d2da394d00175acaeb63758d",
    "/default~InfiniteBabeL~index-es2015.65e2a921e229a535ec50.js": "146ff1deb139b537e10703ad29caf752757691e8",
    "/default~InfiniteBabeL~index-es5.65e2a921e229a535ec50.js": "146ff1deb139b537e10703ad29caf752757691e8",
    "/default~JekyllAndHyde~index-es2015.3625700799411db82b14.js": "ba918a50cc7df36e3a8cb6b0c67b90d7361fcd53",
    "/default~JekyllAndHyde~index-es5.3625700799411db82b14.js": "a2e0186ab7e2feb0e928848f083d3b61c1328587",
    "/default~KanColle~index-es2015.6514369b5766f27eadfb.js": "6ededa1d96a92454f6d0d0a181add66c74a7866d",
    "/default~KanColle~index-es5.6514369b5766f27eadfb.js": "6ededa1d96a92454f6d0d0a181add66c74a7866d",
    "/default~KillDeathBusiness_Korean~index-es2015.6a4ccd42a669648cd5ed.js": "5eaf2d15bf32f4fb75980be1e74a7d6857c23190",
    "/default~KillDeathBusiness_Korean~index-es5.6a4ccd42a669648cd5ed.js": "f4aac4db75bfbae91dcfd9a06f7ba81208762e64",
    "/default~LiveraDoll~index-es2015.2e4e38da0f671e55b4f0.js": "762f840fc2dff8563a6a445802e6c80763370ac8",
    "/default~LiveraDoll~index-es5.2e4e38da0f671e55b4f0.js": "762f840fc2dff8563a6a445802e6c80763370ac8",
    "/default~LogHorizon_Korean~index-es2015.1c1e479ddb51e1d0e310.js": "bb61eaeaa6f9be6d6b1eaf5603a9bdf1139dd282",
    "/default~LogHorizon_Korean~index-es5.1c1e479ddb51e1d0e310.js": "e255e31ace060016ce25b7a28d80ccea6ecfc44c",
    "/default~LogHorizon~index-es2015.b955290a6fa96be4f50b.js": "862540926386ccfaac72b63375ee0a95427788fb",
    "/default~LogHorizon~index-es5.b955290a6fa96be4f50b.js": "a8dab6b87e49aa3bbe46592492a58a3793c8b50c",
    "/default~MagicaLogia_Korean~index-es2015.22b083655f95970c99cd.js": "02399c651cad3c8840b8f00d91f628b3541b0c1a",
    "/default~MagicaLogia_Korean~index-es5.22b083655f95970c99cd.js": "9a80478a8e487586ce0969d47631892581a454ef",
    "/default~MagicaLogia_SimplifiedChinese~index-es2015.f2a4e4ca082c30637350.js": "ac6cc24b66256873eed6597bfdb927b43f60f5ca",
    "/default~MagicaLogia_SimplifiedChinese~index-es5.f2a4e4ca082c30637350.js": "15f5c9b5c3cf49388e7f19856059600b30403ec3",
    "/default~MagicaLogia~index-es2015.31c0b38a05dd018dfbb7.js": "ec52d6d945d031f6b7e811a3a49a27c70b61de6f",
    "/default~MagicaLogia~index-es5.31c0b38a05dd018dfbb7.js": "1a82dbd9fe6da1f72a91d9c158feb2937e2002f9",
    "/default~MeikyuDays~index-es2015.fbdd82fe9b1fef64165a.js": "dec99c75ba7f993862317d5578bdb640b8cf172f",
    "/default~MeikyuDays~index-es5.fbdd82fe9b1fef64165a.js": "dec99c75ba7f993862317d5578bdb640b8cf172f",
    "/default~MeikyuKingdomBasic~index-es2015.de6d946e008d450a2ebd.js": "562e3dbf61cf83d31dbe21f4b2ae99ca1a39e3bb",
    "/default~MeikyuKingdomBasic~index-es5.de6d946e008d450a2ebd.js": "ce1114652c7a5a6d3d3fd23dca591c388798d0d5",
    "/default~MeikyuKingdom~index-es2015.10706d48870ce3d8d810.js": "4295acbd751947846e90ed72099a8198964ddec6",
    "/default~MeikyuKingdom~index-es5.10706d48870ce3d8d810.js": "820f7a09a7f6a9238f6286a6c8eac3d582943905",
    "/default~MetalHeadExtream~index-es2015.3045331b20fd8614500d.js": "40db406585e5ac079823795deb6a08d8b3901d3b",
    "/default~MetalHeadExtream~index-es5.3045331b20fd8614500d.js": "40db406585e5ac079823795deb6a08d8b3901d3b",
    "/default~NeverCloud~index-es2015.6f12589ca732079aa27c.js": "76e409fa7dbd239c213c6186aa6137a9f4206fba",
    "/default~NeverCloud~index-es5.6f12589ca732079aa27c.js": "76e409fa7dbd239c213c6186aa6137a9f4206fba",
    "/default~NinjaSlayer~index-es2015.a534a538a5ab3588bb11.js": "cad92d92a28d06da972248d668166e16520ed20c",
    "/default~NinjaSlayer~index-es5.a534a538a5ab3588bb11.js": "cad92d92a28d06da972248d668166e16520ed20c",
    "/default~OneWayHeroics~index-es2015.59b4ee0244262758ac35.js": "711a091545b15f4447720545b8fea70f9d00bd75",
    "/default~OneWayHeroics~index-es5.59b4ee0244262758ac35.js": "711a091545b15f4447720545b8fea70f9d00bd75",
    "/default~Paradiso~index-es2015.8e529859f2fe8e6c9309.js": "7f57ff1a80ae94d8480f2faf8d99c2c40b342ea8",
    "/default~Paradiso~index-es5.8e529859f2fe8e6c9309.js": "7f57ff1a80ae94d8480f2faf8d99c2c40b342ea8",
    "/default~ParasiteBlood~index-es2015.77da9c9e98c178df9c6c.js": "bebec3c5656ead9c6956c1e9be1f29452e5dde6f",
    "/default~ParasiteBlood~index-es5.77da9c9e98c178df9c6c.js": "bebec3c5656ead9c6956c1e9be1f29452e5dde6f",
    "/default~PulpCthulhu~index-es2015.4d288315c05a4ada111e.js": "26802c820c81e0af61222f17a772c31c3d326b4b",
    "/default~PulpCthulhu~index-es5.4d288315c05a4ada111e.js": "26802c820c81e0af61222f17a772c31c3d326b4b",
    "/default~RuinBreakers~index-es2015.aee5143936999d48c664.js": "fb415e9898533c14795f1be026263190cadfb931",
    "/default~RuinBreakers~index-es5.aee5143936999d48c664.js": "694c926db73a8450e7ddf4e3f4bea0dc0edfcb2f",
    "/default~SamsaraBallad~index-es2015.1a8bcf724d219519065c.js": "93d42e994fbd1299840e61f9c96e906cb1c41f8e",
    "/default~SamsaraBallad~index-es5.1a8bcf724d219519065c.js": "dff474458e98795ceee332feb486de105d9a15f3",
    "/default~Satasupe~index-es2015.1339e683a9d5ca022891.js": "4febb3f5405b02b027c0bc775aac20daac241596",
    "/default~Satasupe~index-es5.1339e683a9d5ca022891.js": "3b3dae88730e776f9ab7d361b98f91e6eddda0dc",
    "/default~ScreamHighSchool~index-es2015.752d5ae11ceca232f651.js": "175a552527f0678f762337b387f90ab0b5785618",
    "/default~ScreamHighSchool~index-es5.752d5ae11ceca232f651.js": "175a552527f0678f762337b387f90ab0b5785618",
    "/default~ShinkuuGakuen~index-es2015.a22d4443a9c4eee656d1.js": "732d79a31781037cac4db579c466c9e81f9fd69b",
    "/default~ShinkuuGakuen~index-es5.a22d4443a9c4eee656d1.js": "732d79a31781037cac4db579c466c9e81f9fd69b",
    "/default~ShinobiGami~index-es2015.3ae6794cd518e6e72420.js": "410c1cd51ce2916232201e48b9431287dcba3815",
    "/default~ShinobiGami~index-es5.3ae6794cd518e6e72420.js": "410c1cd51ce2916232201e48b9431287dcba3815",
    "/default~ShoujoTenrankai~index-es2015.bf295b8a90d2c698339e.js": "29aebab6674735862210e11c4647484726b011c3",
    "/default~ShoujoTenrankai~index-es5.bf295b8a90d2c698339e.js": "29aebab6674735862210e11c4647484726b011c3",
    "/default~StarryDolls~index-es2015.fa1aa0697b5c9a62e93f.js": "037a91d1af4f4fabe9fabf831a0286a6092f8557",
    "/default~StarryDolls~index-es5.fa1aa0697b5c9a62e93f.js": "037a91d1af4f4fabe9fabf831a0286a6092f8557",
    "/default~SteamPunkers~index-es2015.238cb2078af92b548b85.js": "d9ab5f79b0be06197c9a6ff80db15b2c4b7832f9",
    "/default~SteamPunkers~index-es5.238cb2078af92b548b85.js": "c18d2aa1a1e2c6b3c005c14f13ad69f2fe5ed682",
    "/default~SterileLife~index-es2015.0026cb2e50c5d5cd87b6.js": "6e00227e0bad2330ba3240cef4471baf9332fb4c",
    "/default~SterileLife~index-es5.0026cb2e50c5d5cd87b6.js": "6e00227e0bad2330ba3240cef4471baf9332fb4c",
    "/default~SwordWorld2_0~index-es2015.da94abcae7ce6b1ce36c.js": "2ecf9f59f822b65c03101890d218af05017c4bf9",
    "/default~SwordWorld2_0~index-es5.da94abcae7ce6b1ce36c.js": "490fb69c45c4d0bfa771a8f106c7cc5854170a18",
    "/default~SwordWorld2_5~index-es2015.d3c0972c3c0acc5a1cfd.js": "5beed53bc213b92c7f84de0961b004ac356e899f",
    "/default~SwordWorld2_5~index-es5.d3c0972c3c0acc5a1cfd.js": "f04264375af6a4ca60d73420dce6a0fdbd3924e4",
    "/default~SwordWorld~index-es2015.cd6bd0d45b18a2a451b3.js": "f8eaa2d3b6f9bc80179ff21d86f877c42934cdc8",
    "/default~SwordWorld~index-es5.cd6bd0d45b18a2a451b3.js": "ed8896e8546318a09e872e01b3fe366c5f1dc8c8",
    "/default~TwilightGunsmoke~index-es2015.565a4f1eacb6b7ecfcb4.js": "9566e6f69a444433fc48daf71b93f14206061688",
    "/default~TwilightGunsmoke~index-es5.565a4f1eacb6b7ecfcb4.js": "9566e6f69a444433fc48daf71b93f14206061688",
    "/default~UnsungDuet~index-es2015.0ad8a39adef332cbd7ac.js": "897700c1242ac3c2e5b39a444c94d6162593ac1f",
    "/default~UnsungDuet~index-es5.0ad8a39adef332cbd7ac.js": "6ea70a51f1c098511a394e2333311246512dfab2",
    "/default~Villaciel~index-es2015.6b5473a1c4b56cf43e1d.js": "5948d6e4ae517c1ea690820cad51328c2523e631",
    "/default~Villaciel~index-es5.6b5473a1c4b56cf43e1d.js": "5948d6e4ae517c1ea690820cad51328c2523e631",
    "/default~Yggdrasill~index-es2015.3a977f307932b9d3bf90.js": "8bc6385955d69e0bae1d0a4699ccc7ca25b0daf2",
    "/default~Yggdrasill~index-es5.3a977f307932b9d3bf90.js": "c2ec90a5d038970d5275cff4e11ac949c5ec510f",
    "/default~ZettaiReido~index-es2015.8879daf92e1388110a8c.js": "f2f14d7e15df7769cd63a404c7772070dcf5a236",
    "/default~ZettaiReido~index-es5.8879daf92e1388110a8c.js": "ded1101911727464454b71f7a84a9c7313a9fa75",
    "/favicon.ico": "ae0e7ac661ac4b0ee786fef52d313d7655e842cd",
    "/index-es2015.646f52b092930fc37cfc.js": "d9d24277965a877067d967eb5e3b70445755e676",
    "/index-es5.646f52b092930fc37cfc.js": "d9d24277965a877067d967eb5e3b70445755e676",
    "/index.html": "18b63e72331d366e6ddf69344bf96f5d2b9e48f8",
    "/main-es2015.059f5c3a64225a277bf8.js": "bcba539459eba81068a868b7ecdf99d8fb51fbc4",
    "/main-es5.059f5c3a64225a277bf8.js": "8400b20ac39ffca08d1ca8350de63d37625d63c8",
    "/manifest.webmanifest": "3b10b1c25ba6d3eec6d9f8ed16bd8c543fba9ee7",
    "/polyfills-es2015.44e87f6129a4288047f5.js": "54da716e7167fc48cbffa4f27e71a69de9d5d478",
    "/polyfills-es5.bf7e2fc3be6087042749.js": "8881e7e7619d89c6b160b48faa542d1bbc7d7b31",
    "/runtime-es2015.5f4baccca0a1c4e6cf19.js": "7c5c8a2ea6ba091900699b3f47ce3779320ae32e",
    "/runtime-es5.5f4baccca0a1c4e6cf19.js": "0e3abb27cb8875a8edb90d697169efa002f39d23",
    "/styles.280e991c5992f8630bc9.css": "da39a3ee5e6b4b0d3255bfef95601890afd80709"
  },
  "navigationUrls": [
    {
      "positive": true,
      "regex": "^\\/.*$"
    },
    {
      "positive": false,
      "regex": "^\\/(?:.+\\/)?[^/]*\\.[^/]*$"
    },
    {
      "positive": false,
      "regex": "^\\/(?:.+\\/)?[^/]*__[^/]*$"
    },
    {
      "positive": false,
      "regex": "^\\/(?:.+\\/)?[^/]*__[^/]*\\/.*$"
    }
  ],
  "navigationRequestStrategy": "performance"
}